remucs/__init__.py
remucs/__main__.py
remucs/analysis.py
remucs/common.py
remucs/options.py
remucs/remucs.py
remucs/synthesis.py
remucs/utils.py
remucs-0.4.dist-info/LICENSE
remucs-0.4.dist-info/METADATA
remucs-0.4.dist-info/WHEEL
remucs-0.4.dist-info/entry_points.txt
remucs-0.4.dist-info/top_level.txt
remucs-0.4.dist-info/RECORD
