Metadata-Version: 2.1
Name: remucs
Version: 0.4
Summary: Demucs wrapper for remixing audio files with additional customizations
Author-email: Juergen Hock <juergen.hock@jurihock.de>
License: MIT License
Project-URL: Homepage, https://github.com/jurihock/remucs
Project-URL: Documentation, https://github.com/jurihock/remucs/blob/main/README.md
Project-URL: Repository, https://github.com/jurihock/remucs.git
Project-URL: Issues, https://github.com/jurihock/remucs/issues
Keywords: digital,audio,signal,processing,dasp,dafx,effects,filter,demucs,frequency,phase,spectrum,algorithms,analysis,synthesis
Classifier: Intended Audience :: Developers
Classifier: Intended Audience :: Education
Classifier: Intended Audience :: Other Audience
Classifier: Intended Audience :: Science/Research
Classifier: License :: OSI Approved :: MIT License
Classifier: Programming Language :: Python :: 3
Classifier: Topic :: Artistic Software
Classifier: Topic :: Education
Classifier: Topic :: Multimedia :: Sound/Audio :: Analysis
Classifier: Topic :: Multimedia :: Sound/Audio :: Sound Synthesis
Classifier: Topic :: Multimedia :: Sound/Audio
Classifier: Topic :: Scientific/Engineering
Classifier: Topic :: Software Development :: Libraries
Requires-Python: >=3.11
License-File: LICENSE
Requires-Dist: click
Requires-Dist: numpy
Requires-Dist: soundfile
Requires-Dist: stftpitchshift
Requires-Dist: tqdm
Provides-Extra: demucs
Requires-Dist: demucs >=4.0 ; extra == 'demucs'
